cloudless/__init__.py
cloudless/__version__.py
cloudless/image.py
cloudless/log.py
cloudless/network.py
cloudless/paths.py
cloudless/profile.py
cloudless/service.py
cloudless/cli/__init__.py
cloudless/cli/cldls.py
cloudless/cli/image.py
cloudless/cli/image_build.py
cloudless/cli/init.py
cloudless/cli/main.py
cloudless/cli/network.py
cloudless/cli/paths.py
cloudless/cli/service.py
cloudless/cli/service_test.py
cloudless/cli/utils.py
cloudless/cloudless-core-model/models/firewall.json
cloudless/cloudless-core-model/models/image.json
cloudless/cloudless-core-model/models/network.json
cloudless/cloudless-core-model/models/private-network.json
cloudless/cloudless-core-model/models/subnet.json
cloudless/cloudless-core-model/models/virtual-machine.json
cloudless/model/__init__.py
cloudless/providers/__init__.py
cloudless/providers/aws/__init__.py
cloudless/providers/aws/firewall.py
cloudless/providers/aws/image.py
cloudless/providers/aws/image_model.py
cloudless/providers/aws/log.py
cloudless/providers/aws/model.py
cloudless/providers/aws/network.py
cloudless/providers/aws/network_model.py
cloudless/providers/aws/paths.py
cloudless/providers/aws/schemas.py
cloudless/providers/aws/service.py
cloudless/providers/aws/subnet_model.py
cloudless/providers/aws/impl/__init__.py
cloudless/providers/aws/impl/asg.py
cloudless/providers/aws/impl/availability_zones.py
cloudless/providers/aws/impl/image.py
cloudless/providers/aws/impl/internet_gateways.py
cloudless/providers/aws/impl/network.py
cloudless/providers/aws/impl/paths.py
cloudless/providers/aws/impl/security_groups.py
cloudless/providers/aws/impl/service.py
cloudless/providers/aws/impl/subnets.py
cloudless/providers/aws/impl/subnetwork.py
cloudless/providers/aws_mock/__init__.py
cloudless/providers/aws_mock/firewall.py
cloudless/providers/aws_mock/image.py
cloudless/providers/aws_mock/image_model.py
cloudless/providers/aws_mock/model.py
cloudless/providers/aws_mock/network.py
cloudless/providers/aws_mock/network_model.py
cloudless-0.0.10.dist-info/LICENSE
cloudless-0.0.10.dist-info/METADATA
cloudless-0.0.10.dist-info/WHEEL
cloudless-0.0.10.dist-info/entry_points.txt
cloudless-0.0.10.dist-info/top_level.txt
cloudless-0.0.10.dist-info/RECORD
