Metadata-Version: 2.1
Name: cloudless
Version: 0.0.10
Summary: The cloudless infrastructure project.
Home-page: https://github.com/sverch/cloudless
Author: Shaun Verch
Author-email: shaun@getcloudless.com
License: Apache 2.0
Platform: UNKNOWN
Classifier: License :: OSI Approved :: Apache Software License
Classifier: Programming Language :: Python
Classifier: Programming Language :: Python :: 3
Classifier: Programming Language :: Python :: 3.6
Classifier: Programming Language :: Python :: Implementation :: CPython
Classifier: Programming Language :: Python :: Implementation :: PyPy
Requires-Python: >=3.6.0
Requires-Dist: boto3 (==1.9.202)
Requires-Dist: botocore (==1.12.202)
Requires-Dist: PyYAML (==5.1.2)
Requires-Dist: Jinja2 (==2.10.1)
Requires-Dist: pytest (==5.0.1)
Requires-Dist: attr (==0.3.1)
Requires-Dist: Click (==7.0)
Requires-Dist: click-repl (==0.1.6)
Requires-Dist: apache-libcloud (==2.5.0)
Requires-Dist: pycryptodome (==3.8.2)
Requires-Dist: jsonschema (==3.0.2)
Requires-Dist: jsonref (==0.2)
Requires-Dist: cattrs (==0.9.0)
Requires-Dist: moto (==1.3.13)
Requires-Dist: lazy-import (==0.2.2)
Requires-Dist: retrying (==1.3.3)
Requires-Dist: paramiko (==2.6.0)
Provides-Extra: testing
Requires-Dist: pytest (==5.0.1) ; extra == 'testing'
Requires-Dist: pytest-xdist (==1.29.0) ; extra == 'testing'
Requires-Dist: tox (==3.13.2) ; extra == 'testing'
Requires-Dist: pylint (==2.3.1) ; extra == 'testing'
